Workbook

Sheet Einstieg
B4: ERSTE SCHRITTE MIT DEM
B5: CUSTOMER-RELATIONSHIP- MANAGER-BERICHT
B7: Wenn Sie auf der Suche nach einem System sind, mit dem sich Ihre Kontakte organisieren, Verkaufsprozesse konkretisieren und einige Ihrer laufenden Aufgaben automatisieren lassen, ist eine Customer-Relationship-Management-Lösung genau das Richtige für Sie. Diese Vorlage bietet Ihnen die Customer-Relationship-Manager-Grundlagen und eignet sich hervorragend für einen Einstieg, wenn Sie lieber noch kein fortgeschrittenes Customer-Relationship-Manager-System mit erweiterten Funktionen nutzen möchten. Sie ist sozusagen eine Customer-Relationship-Manager- Miniversion, die Änderungen automatisch speichert, sodass Ihnen niemals Daten verloren gehen. Für den Anfang können Sie Ihre Kontakte entweder manuell in die Tabellen eingeben oder vorhandene Daten kopieren und in die Tabelle einfügen.
B16: So verwenden Sie die Vorlage:
B19: 1 | C19: Gehen Sie beim erstmaligen Einrichten der Customer-Relationship-Manager- Miniversion zum Tab "Rahmenbedingungen" und definieren Sie dort Kategorien für Merkmale wie den Kontakttyp bei Personen oder die Phase bei Geschäftschancen. | E19: 2 | F19: Halten Sie den Customer-Relationship- Manager auf dem neuesten Stand, indem Sie in den Tabellen "Personen", "Unternehmen" und "Geschäftschancen" Zeilen aktualisieren oder hinzufügen. | H19: 3 | I19: Nutzen Sie den Customer-Relationship- Manager, um Ihre Zielsetzungen auf täglicher, wöchentlicher und monatlicher Basis festzuhalten. Das "Dashboard" bietet eine Zusammenfassung Ihrer Vertriebspipeline und hilft Ihnen so dabei, eventuelle nächste Schritte zu planen.
B23: Hier finden Sie eine detaillierte Beschreibung der unten auf dem Tabellenblatt angezeigten Tabs.
B26: Dashboard
B27: Den Dashboard-Tab können Sie sich als Steuerfeld für Ihre Geschäftschancen vorstellen. Ihnen werden folgende Informationen angezeigt: - Gesamtwert all Ihrer Geschäftschancen - Gesamtzahl der Personen, Unternehmen und Geschäftschancen in diesem Customer-Relationship-Manager - Zahl und Wert der Geschäftschancen pro Phase Dies ist ein guter Ausgangspunkt für das Festhalten Ihrer täglichen Ziele.
B29: Personen
B30: Als Person gilt hier jemand, mit dem Sie bereits Geschäfte tätigen. Dabei kann es sich um einen aktuellen bzw. potenziellen Kunden oder irgendeinen anderen Typ von Kontakt oder Beziehung handeln. Die Person vertritt hier ein Unternehmen, mit dem Sie Geschäfte tätigen möchten.
B33: Unternehmen
B34: Ein Unternehmen ist eine Organisationseinheit, mit der Sie bereits oder vielleicht in naher Zukunft Geschäfte tätigen. Wir stellen uns das Unternehmen gerne als das Gebäude vor, in dem die Personen arbeiten, mit denen Sie Geschäfte tätigen. Der Unternehmensdatensatz stellt den Datensatz der höchsten Ebene dar, an dem wir andere Datensätze wie Personen oder Geschäftschancen ausrichten.
B38: Geschäftschancen
B39: Bei einer Geschäftschance handelt es sich um jede Art einer Geschäftsentwicklungsbemühung, die Sie nachverfolgen und im Laufe eines Prozesses vorantreiben möchten. Sie kann auch als "Deal" oder "Verkauf" bezeichnet werden. Eine Geschäftschance können der Verkauf eines Produkts, Dienste betreffende Abrechnungen oder eine Aktivität sein, die keinen direkten Geldwert hat – z. B. die Ausweitung Ihrer Berichterstattung.
B43: Rahmenbedingungen
B44: Hier können Sie folgende, die Datenregeln in Ihrer Tabelle bestimmende Elemente definieren: - Kontakttyp für Personen und Unternehmen - Phase, Status, Quelle und Grund des Scheiterns von Geschäftschancen Es liegt in Ihrem Interesse, die Angaben genauestens an die Bedürfnisse Ihrer Unternehmensprozesse anzupassen.

Sheet Dashboard
C1: Dashboard
C4: PIPELINE-WERT (aktiv) | F4: GESAMTZAHL DER
C5: =SUMIFS(Opportunities!F4:F27,Opportunities!I4:I27,"<>Gescheitert",Opportunities!I4:I27,"<>Abgebrochen") -> 218580 | G5: =COUNTA(Kontakte!C5:C28) -> 24 | H5: Personen | J5: =COUNTA(Unternehmen!C4:C25) -> 22 | K5: Unternehmen | M5: =COUNTA(Opportunities!B4:B27) -> 24 | N5: Geschäftschancen
C9: davon bereits gewonnen | E9: =SUMIF(Opportunities!I4:I27,"Erfolgreich",Opportunities!F4:F27) -> 101964
C10: gewichtete offene Pipeline | E10: =SUMPRODUCT((Opportunities!I4:I27="Offen")*Opportunities!F4:F27*Opportunities!H4:H27) -> 60535.2
L11: Phase | M11: Anzahl
L12: Bestätigt | M12: =COUNTIF(Opportunities!$E$4:$E$27,L12) -> 6
L13: Nachverfolgung | M13: =COUNTIF(Opportunities!$E$4:$E$27,L13) -> 7
L14: Präsentation | M14: =COUNTIF(Opportunities!$E$4:$E$27,L14) -> 5
L15: Verhandlung | M15: =COUNTIF(Opportunities!$E$4:$E$27,L15) -> 4
L16: Vertrag gesendet | M16: =COUNTIF(Opportunities!$E$4:$E$27,L16) -> 2
L19: Phase | M19: Gesamtwert
C20: Hinweis Dieses CRM bildet die aktive Vertriebspipeline zum Stand Juli 2026 ab, nicht den gesamten Kundenbestand. LeadPilot betreut zum 31.12.2025 insgesamt 66 zahlende Accounts. Der Pipeline-Wert enthält weder gescheiterte noch abgebrochene Geschäftschancen. Verbindliche Preis- und Bestandsdaten: LeadPilot Faktenblatt v1.1. | L20: Bestätigt | M20: =SUMIF(Opportunities!$E$4:$E$27,L20,Opportunities!$F$4:$F$27) -> 101964
L21: Nachverfolgung | M21: =SUMIF(Opportunities!$E$4:$E$27,L21,Opportunities!$F$4:$F$27) -> 21960
L22: Präsentation | M22: =SUMIF(Opportunities!$E$4:$E$27,L22,Opportunities!$F$4:$F$27) -> 37920
L23: Verhandlung | M23: =SUMIF(Opportunities!$E$4:$E$27,L23,Opportunities!$F$4:$F$27) -> 54444
L24: Vertrag gesendet | M24: =SUMIF(Opportunities!$E$4:$E$27,L24,Opportunities!$F$4:$F$27) -> 8172

Sheet Kontakte
C1: Personen | D1: Copper-Tipp ➜ | E1: Als Person gilt hier jemand, mit dem Sie bereits Geschäfte tätigen. Dabei kann es sich um einen aktuellen bzw. potenziellen Kunden oder irgendeinen anderen Kontakttyp handeln. Die Person vertritt hier ein Unternehmen, mit dem Sie Geschäfte tätigen möchten.
B3: Tag | C3: Name | D3: Unternehmen | E3: E-Mail (geschäftlich) | F3: Funktion | G3: Kontakttyp | H3: Telefon (geschäftlich) | I3: Website (geschäftlich) | J3: Adresse | K3: Stadt | L3: PLZ | M3: LinkedIn | N3: Beschreibung
B4: Präsentation | C4: Michael Voss | D4: Voss Antriebstechnik GmbH | E4: =HYPERLINK("mailto:michael.voss@voss-antriebstechnik.de","michael.voss@voss-antriebstechnik.de") -> michael.voss@voss-antriebstechnik.de | F4: Vertriebsleiter | G4: Aktueller Kunde | H4: 0711-4521100 | I4: www.voss-antriebstechnik.de | J4: Industriestraße 14 | K4: Stuttgart | L4: 70173 | M4: =IF(D4="","-",HYPERLINK("http://www.linkedin.com/search/fpsearch?type=people&keywords="&C4&" "&D4&"&pplSearchOrigin=GLHD&pageKey=fps_results")) -> http://www.linkedin.com/search/fpsearch?type=people&keywords=Michael Voss Voss Antriebstechnik GmbH&pplSearchOrigin=GLHD&pageKey=fps_results | N4: Vertriebsleiter bei Voss Antriebstechnik GmbH, zuständig für Entscheidungen rund um Vertriebssoftware.
B5: Nachverfolgung | C5: Petra Rehbach | D5: Rehbach Fördertechnik GmbH | E5: =HYPERLINK("mailto:petra.rehbach@rehbach-foerdertechnik.de","petra.rehbach@rehbach-foerdertechnik.de") -> petra.rehbach@rehbach-foerdertechnik.de | F5: Head of Sales | G5: Potenzieller Kunde | H5: 0711-9834520 | I5: www.rehbach-foerdertechnik.de | J5: Werkstattweg 8 | K5: Esslingen am Neckar | L5: 73728 | M5: =IF(D5="","-",HYPERLINK("http://www.linkedin.com/search/fpsearch?type=people&keywords="&C5&" "&D5&"&pplSearchOrigin=GLHD&pageKey=fps_results")) -> http://www.linkedin.com/search/fpsearch?type=people&keywords=Petra Rehbach Rehbach Fördertechnik GmbH&pplSearchOrigin=GLHD&pageKey=fps_results | N5: Head of Sales bei Rehbach Fördertechnik GmbH, zuständig für Entscheidungen rund um Vertriebssoftware.
B6: Erstkontakt | C6: Frank Kessler | D6: Kessler Präzisionswerk GmbH | E6: =HYPERLINK("mailto:frank.kessler@kessler-praezision.de","frank.kessler@kessler-praezision.de") -> frank.kessler@kessler-praezision.de | F6: Geschäftsführer | G6: Potenzieller Kunde | H6: 07121-558430 | I6: www.kessler-praezision.de | J6: Am Steinbruch 3 | K6: Reutlingen | L6: 72760 | M6: =IF(D6="","-",HYPERLINK("http://www.linkedin.com/search/fpsearch?type=people&keywords="&C6&" "&D6&"&pplSearchOrigin=GLHD&pageKey=fps_results")) -> http://www.linkedin.com/search/fpsearch?type=people&keywords=Frank Kessler Kessler Präzisionswerk GmbH&pplSearchOrigin=GLHD&pageKey=fps_results | N6: Geschäftsführer bei Kessler Präzisionswerk GmbH, zuständig für Entscheidungen rund um Vertriebssoftware.
B7: Upselling | C7: Claudia Brenner | D7: Brenner Hydraulik AG | E7: =HYPERLINK("mailto:claudia.brenner@brenner-hydraulik.de","claudia.brenner@brenner-hydraulik.de") -> claudia.brenner@brenner-hydraulik.de | F7: Vertriebsleiterin | G7: Aktueller Kunde | H7: 07721-609870 | I7: www.brenner-hydraulik.de | J7: Hydraulikring 5 | K7: Villingen-Schwenningen | L7: 78048 | M7: =IF(D7="","-",HYPERLINK("http://www.linkedin.com/search/fpsearch?type=people&keywords="&C7&" "&D7&"&pplSearchOrigin=GLHD&pageKey=fps_results")) -> http://www.linkedin.com/search/fpsearch?type=people&keywords=Claudia Brenner Brenner Hydraulik AG&pplSearchOrigin=GLHD&pageKey=fps_results | N7: Vertriebsleiterin bei Brenner Hydraulik AG, zuständig für Entscheidungen rund um Vertriebssoftware.
B8: Nachverfolgung | C8: Stefan Nordmeyer | D8: Nordmeyer Maschinenbau GmbH & Co. KG | E8: =HYPERLINK("mailto:stefan.nordmeyer@nordmeyer-maschinenbau.de","stefan.nordmeyer@nordmeyer-maschinenbau.de") -> stefan.nordmeyer@nordmeyer-maschinenbau.de | F8: Leiter Vertriebsinnendienst | G8: Potenzieller Kunde | H8: 0521-772340 | I8: www.nordmeyer-maschinenbau.de | J8: Ravensberger Straße 22 | K8: Bielefeld | L8: 33602 | M8: =IF(D8="","-",HYPERLINK("http://www.linkedin.com/search/fpsearch?type=people&keywords="&C8&" "&D8&"&pplSearchOrigin=GLHD&pageKey=fps_results")) -> http://www.linkedin.com/search/fpsearch?type=people&keywords=Stefan Nordmeyer Nordmeyer Maschinenbau GmbH & Co. KG&pplSearchOrigin=GLHD&pageKey=fps_results | N8: Leiter Vertriebsinnendienst bei Nordmeyer Maschinenbau GmbH & Co. KG, zuständig für Entscheidungen rund um Vertriebssoftware.
B9: In Kürze | C9: Robert Falkenrath | D9: Falkenrath Werkzeugmaschinen GmbH | E9: =HYPERLINK("mailto:robert.falkenrath@falkenrath-wzm.de","robert.falkenrath@falkenrath-wzm.de") -> robert.falkenrath@falkenrath-wzm.de | F9: Geschäftsführer | G9: Sonstiger | H9: 0371-458820 | I9: www.falkenrath-wzm.de | J9: Fabrikstraße 61 | K9: Chemnitz | L9: 9111 | M9: =IF(D9="","-",HYPERLINK("http://www.linkedin.com/search/fpsearch?type=people&keywords="&C9&" "&D9&"&pplSearchOrigin=GLHD&pageKey=fps_results")) -> http://www.linkedin.com/search/fpsearch?type=people&keywords=Robert Falkenrath Falkenrath Werkzeugmaschinen GmbH&pplSearchOrigin=GLHD&pageKey=fps_results | N9: Geschäftsführer bei Falkenrath Werkzeugmaschinen GmbH, zuständig für Entscheidungen rund um Vertriebssoftware.
B10: Bestandskunde | C10: Anna Corvin | D10: Corvion Software GmbH | E10: =HYPERLINK("mailto:anna.corvin@corvion-software.de","anna.corvin@corvion-software.de") -> anna.corvin@corvion-software.de | F10: Head of Sales | G10: Aktueller Kunde | H10: 030-2345678 | I10: www.corvion-software.de | J10: Torstraße 101 | K10: Berlin | L10: 10115 | M10: =IF(D10="","-",HYPERLINK("http://www.linkedin.com/search/fpsearch?type=people&keywords="&C10&" "&D10&"&pplSearchOrigin=GLHD&pageKey=fps_results")) -> http://www.linkedin.com/search/fpsearch?type=people&keywords=Anna Corvin Corvion Software GmbH&pplSearchOrigin=GLHD&pageKey=fps_results | N10: Head of Sales bei Corvion Software GmbH, zuständig für Entscheidungen rund um Vertriebssoftware.
B11: Präsentation | C11: Julia Bittner | D11: Bittner IT-Solutions GmbH | E11: =HYPERLINK("mailto:julia.bittner@bittner-it.de","julia.bittner@bittner-it.de") -> julia.bittner@bittner-it.de | F11: Vertriebsleiterin | G11: Potenzieller Kunde | H11: 089-5567234 | I11: www.bittner-it.de | J11: Rosenheimer Straße 47 | K11: München | L11: 80331 | M11: =IF(D11="","-",HYPERLINK("http://www.linkedin.com/search/fpsearch?type=people&keywords="&C11&" "&D11&"&pplSearchOrigin=GLHD&pageKey=fps_results")) -> http://www.linkedin.com/search/fpsearch?type=people&keywords=Julia Bittner Bittner IT-Solutions GmbH&pplSearchOrigin=GLHD&pageKey=fps_results | N11: Vertriebsleiterin bei Bittner IT-Solutions GmbH, zuständig für Entscheidungen rund um Vertriebssoftware.
B12: Erstkontakt | C12: Kevin Pauls | D12: Pixelwerk Digital GmbH | E12: =HYPERLINK("mailto:kevin.pauls@pixelwerk-digital.de","kevin.pauls@pixelwerk-digital.de") -> kevin.pauls@pixelwerk-digital.de | F12: Gründer & Geschäftsführer | G12: Potenzieller Kunde | H12: 040-3345621 | I12: www.pixelwerk-digital.de | J12: Hafenallee 9 | K12: Hamburg | L12: 20095 | M12: =IF(D12="","-",HYPERLINK("http://www.linkedin.com/search/fpsearch?type=people&keywords="&C12&" "&D12&"&pplSearchOrigin=GLHD&pageKey=fps_results")) -> http://www.linkedin.com/search/fpsearch?type=people&keywords=Kevin Pauls Pixelwerk Digital GmbH&pplSearchOrigin=GLHD&pageKey=fps_results | N12: Gründer & Geschäftsführer bei Pixelwerk Digital GmbH, zuständig für Entscheidungen rund um Vertriebssoftware.
B13: Bestandskunde | C13: Nadine Kurz | D13: Nexora Systems GmbH | E13: =HYPERLINK("mailto:nadine.kurz@nexora-systems.de","nadine.kurz@nexora-systems.de") -> nadine.kurz@nexora-systems.de | F13: Sales Managerin | G13: Aktueller Kunde | H13: 0221-9987654 | I13: www.nexora-systems.de | J13: Rheinauhafen 12 | K13: Köln | L13: 50667 | M13: =IF(D13="","-",HYPERLINK("http://www.linkedin.com/search/fpsearch?type=people&keywords="&C13&" "&D13&"&pplSearchOrigin=GLHD&pageKey=fps_results")) -> http://www.linkedin.com/search/fpsearch?type=people&keywords=Nadine Kurz Nexora Systems GmbH&pplSearchOrigin=GLHD&pageKey=fps_results | N13: Sales Managerin bei Nexora Systems GmbH, zuständig für Entscheidungen rund um Vertriebssoftware.
B14: Nachverfolgung | C14: Tobias Vogt | D14: Vantis Cloud Services GmbH | E14: =HYPERLINK("mailto:tobias.vogt@vantis-cloud.de","tobias.vogt@vantis-cloud.de") -> tobias.vogt@vantis-cloud.de | F14: Geschäftsführer | G14: Potenzieller Kunde | H14: 0341-2213456 | I14: www.vantis-cloud.de | J14: Karl-Liebknecht-Straße 30 | K14: Leipzig | L14: 4109 | M14: =IF(D14="","-",HYPERLINK("http://www.linkedin.com/search/fpsearch?type=people&keywords="&C14&" "&D14&"&pplSearchOrigin=GLHD&pageKey=fps_results")) -> http://www.linkedin.com/search/fpsearch?type=people&keywords=Tobias Vogt Vantis Cloud Services GmbH&pplSearchOrigin=GLHD&pageKey=fps_results | N14: Geschäftsführer bei Vantis Cloud Services GmbH, zuständig für Entscheidungen rund um Vertriebssoftware.
B15: Präsentation | C15: Sabine Dornbach | D15: Dornbach IT Consulting GmbH | E15: =HYPERLINK("mailto:sabine.dornbach@dornbach-consulting.de","sabine.dornbach@dornbach-consulting.de") -> sabine.dornbach@dornbach-consulting.de | F15: Partnerin | G15: Potenzieller Kunde | H15: 069-8834521 | I15: www.dornbach-consulting.de | J15: Mainzer Landstraße 250 | K15: Frankfurt am Main | L15: 60311 | M15: =IF(D15="","-",HYPERLINK("http://www.linkedin.com/search/fpsearch?type=people&keywords="&C15&" "&D15&"&pplSearchOrigin=GLHD&pageKey=fps_results")) -> http://www.linkedin.com/search/fpsearch?type=people&keywords=Sabine Dornbach Dornbach IT Consulting GmbH&pplSearchOrigin=GLHD&pageKey=fps_results | N15: Partnerin bei Dornbach IT Consulting GmbH, zuständig für Entscheidungen rund um Vertriebssoftware.
B16: Bestandskunde | C16: Markus Reimann | D16: Reimann Großhandel GmbH | E16: =HYPERLINK("mailto:markus.reimann@reimann-grosshandel.de","markus.reimann@reimann-grosshandel.de") -> markus.reimann@reimann-grosshandel.de | F16: Vertriebsleiter | G16: Aktueller Kunde | H16: 0231-556723 | I16: www.reimann-grosshandel.de | J16: Speicherstraße 18 | K16: Dortmund | L16: 44135 | M16: =IF(D16="","-",HYPERLINK("http://www.linkedin.com/search/fpsearch?type=people&keywords="&C16&" "&D16&"&pplSearchOrigin=GLHD&pageKey=fps_results")) -> http://www.linkedin.com/search/fpsearch?type=people&keywords=Markus Reimann Reimann Großhandel GmbH&pplSearchOrigin=GLHD&pageKey=fps_results | N16: Vertriebsleiter bei Reimann Großhandel GmbH, zuständig für Entscheidungen rund um Vertriebssoftware.
B17: Verhandlung | C17: Susanne Kaltenbach | D17: Kaltenbach Baustoffhandel GmbH | E17: =HYPERLINK("mailto:susanne.kaltenbach@kaltenbach-baustoff.de","susanne.kaltenbach@kaltenbach-baustoff.de") -> susanne.kaltenbach@kaltenbach-baustoff.de | F17: Head of Sales | G17: Potenzieller Kunde | H17: 0621-778234 | I17: www.kaltenbach-baustoff.de | J17: Industriekai 4 | K17: Mannheim | L17: 68159 | M17: =IF(D17="","-",HYPERLINK("http://www.linkedin.com/search/fpsearch?type=people&keywords="&C17&" "&D17&"&pplSearchOrigin=GLHD&pageKey=fps_results")) -> http://www.linkedin.com/search/fpsearch?type=people&keywords=Susanne Kaltenbach Kaltenbach Baustoffhandel GmbH&pplSearchOrigin=GLHD&pageKey=fps_results | N17: Head of Sales bei Kaltenbach Baustoffhandel GmbH, zuständig für Entscheidungen rund um Vertriebssoftware.
B18: Bestandskunde | C18: Heiko Nordfrost | D18: Nordfrost Getränkehandel GmbH | E18: =HYPERLINK("mailto:heiko.nordfrost@nordfrost-getraenke.de","heiko.nordfrost@nordfrost-getraenke.de") -> heiko.nordfrost@nordfrost-getraenke.de | F18: Vertriebsleiter | G18: Aktueller Kunde | H18: 0421-334521 | I18: www.nordfrost-getraenke.de | J18: Überseering 6 | K18: Bremen | L18: 28195 | M18: =IF(D18="","-",HYPERLINK("http://www.linkedin.com/search/fpsearch?type=people&keywords="&C18&" "&D18&"&pplSearchOrigin=GLHD&pageKey=fps_results")) -> http://www.linkedin.com/search/fpsearch?type=people&keywords=Heiko Nordfrost Nordfrost Getränkehandel GmbH&pplSearchOrigin=GLHD&pageKey=fps_results | N18: Vertriebsleiter bei Nordfrost Getränkehandel GmbH, zuständig für Entscheidungen rund um Vertriebssoftware.
B19: Nachverfolgung | C19: Katrin Ostmann | D19: Ostmann Elektrogroßhandel GmbH | E19: =HYPERLINK("mailto:katrin.ostmann@ostmann-elektro.de","katrin.ostmann@ostmann-elektro.de") -> katrin.ostmann@ostmann-elektro.de | F19: Leiterin Vertriebsinnendienst | G19: Potenzieller Kunde | H19: 0511-667234 | I19: www.ostmann-elektro.de | J19: Vahrenwalder Straße 205 | K19: Hannover | L19: 30159 | M19: =IF(D19="","-",HYPERLINK("http://www.linkedin.com/search/fpsearch?type=people&keywords="&C19&" "&D19&"&pplSearchOrigin=GLHD&pageKey=fps_results")) -> http://www.linkedin.com/search/fpsearch?type=people&keywords=Katrin Ostmann Ostmann Elektrogroßhandel GmbH&pplSearchOrigin=GLHD&pageKey=fps_results | N19: Leiterin Vertriebsinnendienst bei Ostmann Elektrogroßhandel GmbH, zuständig für Entscheidungen rund um Vertriebssoftware.
B20: In Kürze | C20: Dirk Wendland | D20: Wendland Agrarhandel GmbH | E20: =HYPERLINK("mailto:dirk.wendland@wendland-agrar.de","dirk.wendland@wendland-agrar.de") -> dirk.wendland@wendland-agrar.de | F20: Geschäftsführer | G20: Sonstiger | H20: 0391-445621 | I20: www.wendland-agrar.de | J20: Kathedralstraße 9 | K20: Magdeburg | L20: 39104 | M20: =IF(D20="","-",HYPERLINK("http://www.linkedin.com/search/fpsearch?type=people&keywords="&C20&" "&D20&"&pplSearchOrigin=GLHD&pageKey=fps_results")) -> http://www.linkedin.com/search/fpsearch?type=people&keywords=Dirk Wendland Wendland Agrarhandel GmbH&pplSearchOrigin=GLHD&pageKey=fps_results | N20: Geschäftsführer bei Wendland Agrarhandel GmbH, zuständig für Entscheidungen rund um Vertriebssoftware.
B21: Bestandskunde | C21: Lea Kreativ | D21: Kreativkraft Werbeagentur GmbH | E21: =HYPERLINK("mailto:lea.kreativ@kreativkraft-agentur.de","lea.kreativ@kreativkraft-agentur.de") -> lea.kreativ@kreativkraft-agentur.de | F21: Geschäftsführerin | G21: Aktueller Kunde | H21: 0211-887234 | I21: www.kreativkraft-agentur.de | J21: Kö-Bogen 3 | K21: Düsseldorf | L21: 40210 | M21: =IF(D21="","-",HYPERLINK("http://www.linkedin.com/search/fpsearch?type=people&keywords="&C21&" "&D21&"&pplSearchOrigin=GLHD&pageKey=fps_results")) -> http://www.linkedin.com/search/fpsearch?type=people&keywords=Lea Kreativ Kreativkraft Werbeagentur GmbH&pplSearchOrigin=GLHD&pageKey=fps_results | N21: Geschäftsführerin bei Kreativkraft Werbeagentur GmbH, zuständig für Entscheidungen rund um Vertriebssoftware.
B22: Erstkontakt | C22: Simon Blau | D22: Blaupause Kommunikation GmbH | E22: =HYPERLINK("mailto:simon.blau@blaupause-kommunikation.de","simon.blau@blaupause-kommunikation.de") -> simon.blau@blaupause-kommunikation.de | F22: Gründer & Geschäftsführer | G22: Potenzieller Kunde | H22: 0911-556234 | I22: www.blaupause-kommunikation.de | J22: Königstraße 55 | K22: Nürnberg | L22: 90402 | M22: =IF(D22="","-",HYPERLINK("http://www.linkedin.com/search/fpsearch?type=people&keywords="&C22&" "&D22&"&pplSearchOrigin=GLHD&pageKey=fps_results")) -> http://www.linkedin.com/search/fpsearch?type=people&keywords=Simon Blau Blaupause Kommunikation GmbH&pplSearchOrigin=GLHD&pageKey=fps_results | N22: Gründer & Geschäftsführer bei Blaupause Kommunikation GmbH, zuständig für Entscheidungen rund um Vertriebssoftware.
B23: Erstkontakt | C23: Nina Funke | D23: Funkeis Markenagentur GmbH | E23: =HYPERLINK("mailto:nina.funke@funkeis-marken.de","nina.funke@funkeis-marken.de") -> nina.funke@funkeis-marken.de | F23: Geschäftsführerin | G23: Potenzieller Kunde | H23: 0341-778934 | I23: www.funkeis-marken.de | J23: Nikolaistraße 15 | K23: Leipzig | L23: 4105 | M23: =IF(D23="","-",HYPERLINK("http://www.linkedin.com/search/fpsearch?type=people&keywords="&C23&" "&D23&"&pplSearchOrigin=GLHD&pageKey=fps_results")) -> http://www.linkedin.com/search/fpsearch?type=people&keywords=Nina Funke Funkeis Markenagentur GmbH&pplSearchOrigin=GLHD&pageKey=fps_results | N23: Geschäftsführerin bei Funkeis Markenagentur GmbH, zuständig für Entscheidungen rund um Vertriebssoftware.
B24: Bestandskunde | C24: Paul Aurelius | D24: Aurora Media Group GmbH | E24: =HYPERLINK("mailto:paul.aurelius@aurora-media-group.de","paul.aurelius@aurora-media-group.de") -> paul.aurelius@aurora-media-group.de | F24: Head of Sales | G24: Aktueller Kunde | H24: 0221-334521 | I24: www.aurora-media-group.de | J24: Ehrenstraße 88 | K24: Köln | L24: 50672 | M24: =IF(D24="","-",HYPERLINK("http://www.linkedin.com/search/fpsearch?type=people&keywords="&C24&" "&D24&"&pplSearchOrigin=GLHD&pageKey=fps_results")) -> http://www.linkedin.com/search/fpsearch?type=people&keywords=Paul Aurelius Aurora Media Group GmbH&pplSearchOrigin=GLHD&pageKey=fps_results | N24: Head of Sales bei Aurora Media Group GmbH, zuständig für Entscheidungen rund um Vertriebssoftware.
B25: Nachverfolgung | C25: Merle Nord | D25: Studio Nordlicht GmbH | E25: =HYPERLINK("mailto:merle.nord@studio-nordlicht.de","merle.nord@studio-nordlicht.de") -> merle.nord@studio-nordlicht.de | F25: Gründerin | G25: Potenzieller Kunde | H25: 0431-667823 | I25: www.studio-nordlicht.de | J25: Holstenstraße 41 | K25: Kiel | L25: 24103 | M25: =IF(D25="","-",HYPERLINK("http://www.linkedin.com/search/fpsearch?type=people&keywords="&C25&" "&D25&"&pplSearchOrigin=GLHD&pageKey=fps_results")) -> http://www.linkedin.com/search/fpsearch?type=people&keywords=Merle Nord Studio Nordlicht GmbH&pplSearchOrigin=GLHD&pageKey=fps_results | N25: Gründerin bei Studio Nordlicht GmbH, zuständig für Entscheidungen rund um Vertriebssoftware.
B26: Präsentation | C26: Daniel Wagner | D26: Rehbach Fördertechnik GmbH | E26: =HYPERLINK("mailto:daniel.wagner@rehbach-foerdertechnik.de","daniel.wagner@rehbach-foerdertechnik.de") -> daniel.wagner@rehbach-foerdertechnik.de | F26: Vertriebsmitarbeiter | G26: Potenzieller Kunde | H26: 0711-9834520 | I26: www.rehbach-foerdertechnik.de | J26: Werkstattweg 8 | K26: Esslingen am Neckar | L26: 73728 | M26: =IF(D26="","-",HYPERLINK("http://www.linkedin.com/search/fpsearch?type=people&keywords="&C26&" "&D26&"&pplSearchOrigin=GLHD&pageKey=fps_results")) -> http://www.linkedin.com/search/fpsearch?type=people&keywords=Daniel Wagner Rehbach Fördertechnik GmbH&pplSearchOrigin=GLHD&pageKey=fps_results | N26: Vertriebsmitarbeiter bei Rehbach Fördertechnik GmbH, zuständig für Entscheidungen rund um Vertriebssoftware.
B27: Verhandlung | C27: Melanie Groß | D27: Kaltenbach Baustoffhandel GmbH | E27: =HYPERLINK("mailto:melanie.gross@kaltenbach-baustoff.de","melanie.gross@kaltenbach-baustoff.de") -> melanie.gross@kaltenbach-baustoff.de | F27: Einkaufsleiterin | G27: Potenzieller Kunde | H27: 0621-778234 | I27: www.kaltenbach-baustoff.de | J27: Industriekai 4 | K27: Mannheim | L27: 68159 | M27: =IF(D27="","-",HYPERLINK("http://www.linkedin.com/search/fpsearch?type=people&keywords="&C27&" "&D27&"&pplSearchOrigin=GLHD&pageKey=fps_results")) -> http://www.linkedin.com/search/fpsearch?type=people&keywords=Melanie Groß Kaltenbach Baustoffhandel GmbH&pplSearchOrigin=GLHD&pageKey=fps_results | N27: Einkaufsleiterin bei Kaltenbach Baustoffhandel GmbH, zuständig für Entscheidungen rund um Vertriebssoftware.
B28: Bestandskunde | C28: Oliver Stein | D28: Nordfrost Getränkehandel GmbH | E28: =HYPERLINK("mailto:oliver.stein@nordfrost-getraenke.de","oliver.stein@nordfrost-getraenke.de") -> oliver.stein@nordfrost-getraenke.de | F28: IT-Administrator | G28: Aktueller Kunde | H28: 0421-334521 | I28: www.nordfrost-getraenke.de | J28: Überseering 6 | K28: Bremen | L28: 28195 | M28: =IF(D28="","-",HYPERLINK("http://www.linkedin.com/search/fpsearch?type=people&keywords="&C28&" "&D28&"&pplSearchOrigin=GLHD&pageKey=fps_results")) -> http://www.linkedin.com/search/fpsearch?type=people&keywords=Oliver Stein Nordfrost Getränkehandel GmbH&pplSearchOrigin=GLHD&pageKey=fps_results | N28: IT-Administrator bei Nordfrost Getränkehandel GmbH, zuständig für Entscheidungen rund um Vertriebssoftware.

Sheet Unternehmen
C1: Unternehmen | D1: Copper-Tipp ➜ | E1: Ein Unternehmen ist eine Organisationseinheit, mit der Sie bereits oder vielleicht in naher Zukunft Geschäfte tätigen. Sie können durch die Verwendung von Tags verschiedene Unternehmen gruppieren, damit sie sich später leichter filtern lassen.
B3: Tag | C3: Name des Unternehmens | D3: Kontakttyp | E3: Telefon (geschäftlich) | F3: E-Mail-Domain | G3: Website (geschäftlich) | H3: Adresse | I3: Stadt | J3: PLZ | K3: Land | L3: LinkedIn | M3: Verantwortlicher | N3: Beschreibung
B4: Maschinenbau | C4: Voss Antriebstechnik GmbH | D4: Aktueller Kunde | E4: 0711-4521100 | F4: @voss-antriebstechnik.de | G4: www.voss-antriebstechnik.de | H4: Industriestraße 14 | I4: Stuttgart | J4: 70173 | K4: DE | L4: =IF(C4="","-",HYPERLINK("https://www.linkedin.com/vsearch/c?type=companies&keywords="&C4&"&orig=GLHD&rsid=&pageKey=biz-overview-internal&trkInfo=&search=Search")) -> https://www.linkedin.com/vsearch/c?type=companies&keywords=Voss Antriebstechnik GmbH&orig=GLHD&rsid=&pageKey=biz-overview-internal&trkInfo=&search=Search | M4: Jonas Reiter | N4: Bestandskunde seit 2025, nutzt LeadPilot Professional im gesamten Vertriebsteam.
B5: Maschinenbau | C5: Rehbach Fördertechnik GmbH | D5: Potenzieller Kunde | E5: 0711-9834520 | F5: @rehbach-foerdertechnik.de | G5: www.rehbach-foerdertechnik.de | H5: Werkstattweg 8 | I5: Esslingen am Neckar | J5: 73728 | K5: DE | L5: =IF(C5="","-",HYPERLINK("https://www.linkedin.com/vsearch/c?type=companies&keywords="&C5&"&orig=GLHD&rsid=&pageKey=biz-overview-internal&trkInfo=&search=Search")) -> https://www.linkedin.com/vsearch/c?type=companies&keywords=Rehbach Fördertechnik GmbH&orig=GLHD&rsid=&pageKey=biz-overview-internal&trkInfo=&search=Search | M5: Sarah Klein | N5: Sucht Ablösung für Excel-Listen im Vertrieb, aktuell in Demo-Phase.
B6: Maschinenbau | C6: Kessler Präzisionswerk GmbH | D6: Potenzieller Kunde | E6: 07121-558430 | F6: @kessler-praezision.de | G6: www.kessler-praezision.de | H6: Am Steinbruch 3 | I6: Reutlingen | J6: 72760 | K6: DE | L6: =IF(C6="","-",HYPERLINK("https://www.linkedin.com/vsearch/c?type=companies&keywords="&C6&"&orig=GLHD&rsid=&pageKey=biz-overview-internal&trkInfo=&search=Search")) -> https://www.linkedin.com/vsearch/c?type=companies&keywords=Kessler Präzisionswerk GmbH&orig=GLHD&rsid=&pageKey=biz-overview-internal&trkInfo=&search=Search | M6: Tim Brandt | N6: Kontakt über Kaltakquise, Erstgespräch positiv verlaufen.
B7: Maschinenbau | C7: Brenner Hydraulik AG | D7: Aktueller Kunde | E7: 07721-609870 | F7: @brenner-hydraulik.de | G7: www.brenner-hydraulik.de | H7: Hydraulikring 5 | I7: Villingen-Schwenningen | J7: 78048 | K7: DE | L7: =IF(C7="","-",HYPERLINK("https://www.linkedin.com/vsearch/c?type=companies&keywords="&C7&"&orig=GLHD&rsid=&pageKey=biz-overview-internal&trkInfo=&search=Search")) -> https://www.linkedin.com/vsearch/c?type=companies&keywords=Brenner Hydraulik AG&orig=GLHD&rsid=&pageKey=biz-overview-internal&trkInfo=&search=Search | M7: Jonas Reiter | N7: Bestandskunde, Enterprise-Vertrag, Upselling-Gespräch für Marketing-Modul läuft.
B8: Maschinenbau | C8: Nordmeyer Maschinenbau GmbH & Co. KG | D8: Potenzieller Kunde | E8: 0521-772340 | F8: @nordmeyer-maschinenbau.de | G8: www.nordmeyer-maschinenbau.de | H8: Ravensberger Straße 22 | I8: Bielefeld | J8: 33602 | K8: DE | L8: =IF(C8="","-",HYPERLINK("https://www.linkedin.com/vsearch/c?type=companies&keywords="&C8&"&orig=GLHD&rsid=&pageKey=biz-overview-internal&trkInfo=&search=Search")) -> https://www.linkedin.com/vsearch/c?type=companies&keywords=Nordmeyer Maschinenbau GmbH & Co. KG&orig=GLHD&rsid=&pageKey=biz-overview-internal&trkInfo=&search=Search | M8: Sarah Klein | N8: Über Webinar 'Digitaler Vertrieb im Maschinenbau' generiert.
B9: Maschinenbau | C9: Falkenrath Werkzeugmaschinen GmbH | D9: Sonstiger | E9: 0371-458820 | F9: @falkenrath-wzm.de | G9: www.falkenrath-wzm.de | H9: Fabrikstraße 61 | I9: Chemnitz | J9: 9111 | K9: DE | L9: =IF(C9="","-",HYPERLINK("https://www.linkedin.com/vsearch/c?type=companies&keywords="&C9&"&orig=GLHD&rsid=&pageKey=biz-overview-internal&trkInfo=&search=Search")) -> https://www.linkedin.com/vsearch/c?type=companies&keywords=Falkenrath Werkzeugmaschinen GmbH&orig=GLHD&rsid=&pageKey=biz-overview-internal&trkInfo=&search=Search | M9: Nora Vogel | N9: Möglicher Vertriebspartner für Sachsen, noch keine Kaufabsicht.
B10: IT | C10: Corvion Software GmbH | D10: Aktueller Kunde | E10: 030-2345678 | F10: @corvion-software.de | G10: www.corvion-software.de | H10: Torstraße 101 | I10: Berlin | J10: 10115 | K10: DE | L10: =IF(C10="","-",HYPERLINK("https://www.linkedin.com/vsearch/c?type=companies&keywords="&C10&"&orig=GLHD&rsid=&pageKey=biz-overview-internal&trkInfo=&search=Search")) -> https://www.linkedin.com/vsearch/c?type=companies&keywords=Corvion Software GmbH&orig=GLHD&rsid=&pageKey=biz-overview-internal&trkInfo=&search=Search | M10: Jonas Reiter | N10: Bestandskunde, sehr zufrieden, dient als Referenzkunde.
B11: IT | C11: Bittner IT-Solutions GmbH | D11: Potenzieller Kunde | E11: 089-5567234 | F11: @bittner-it.de | G11: www.bittner-it.de | H11: Rosenheimer Straße 47 | I11: München | J11: 80331 | K11: DE | L11: =IF(C11="","-",HYPERLINK("https://www.linkedin.com/vsearch/c?type=companies&keywords="&C11&"&orig=GLHD&rsid=&pageKey=biz-overview-internal&trkInfo=&search=Search")) -> https://www.linkedin.com/vsearch/c?type=companies&keywords=Bittner IT-Solutions GmbH&orig=GLHD&rsid=&pageKey=biz-overview-internal&trkInfo=&search=Search | M11: Tim Brandt | N11: Vergleicht aktuell LeadPilot mit Pipedrive.
B12: IT | C12: Pixelwerk Digital GmbH | D12: Potenzieller Kunde | E12: 040-3345621 | F12: @pixelwerk-digital.de | G12: www.pixelwerk-digital.de | H12: Hafenallee 9 | I12: Hamburg | J12: 20095 | K12: DE | L12: =IF(C12="","-",HYPERLINK("https://www.linkedin.com/vsearch/c?type=companies&keywords="&C12&"&orig=GLHD&rsid=&pageKey=biz-overview-internal&trkInfo=&search=Search")) -> https://www.linkedin.com/vsearch/c?type=companies&keywords=Pixelwerk Digital GmbH&orig=GLHD&rsid=&pageKey=biz-overview-internal&trkInfo=&search=Search | M12: Sarah Klein | N12: Wachstumsstarkes Start-up, erste Demo terminiert.
B13: IT | C13: Nexora Systems GmbH | D13: Aktueller Kunde | E13: 0221-9987654 | F13: @nexora-systems.de | G13: www.nexora-systems.de | H13: Rheinauhafen 12 | I13: Köln | J13: 50667 | K13: DE | L13: =IF(C13="","-",HYPERLINK("https://www.linkedin.com/vsearch/c?type=companies&keywords="&C13&"&orig=GLHD&rsid=&pageKey=biz-overview-internal&trkInfo=&search=Search")) -> https://www.linkedin.com/vsearch/c?type=companies&keywords=Nexora Systems GmbH&orig=GLHD&rsid=&pageKey=biz-overview-internal&trkInfo=&search=Search | M13: Jonas Reiter | N13: Bestandskunde seit Q1 2026, Nutzung wächst stetig.
B14: IT | C14: Vantis Cloud Services GmbH | D14: Potenzieller Kunde | E14: 0341-2213456 | F14: @vantis-cloud.de | G14: www.vantis-cloud.de | H14: Karl-Liebknecht-Straße 30 | I14: Leipzig | J14: 4109 | K14: DE | L14: =IF(C14="","-",HYPERLINK("https://www.linkedin.com/vsearch/c?type=companies&keywords="&C14&"&orig=GLHD&rsid=&pageKey=biz-overview-internal&trkInfo=&search=Search")) -> https://www.linkedin.com/vsearch/c?type=companies&keywords=Vantis Cloud Services GmbH&orig=GLHD&rsid=&pageKey=biz-overview-internal&trkInfo=&search=Search | M14: Tim Brandt | N14: Kleines Team, preissensibel, Interesse am Starter-Plan.
B15: IT | C15: Dornbach IT Consulting GmbH | D15: Potenzieller Kunde | E15: 069-8834521 | F15: @dornbach-consulting.de | G15: www.dornbach-consulting.de | H15: Mainzer Landstraße 250 | I15: Frankfurt am Main | J15: 60311 | K15: DE | L15: =IF(C15="","-",HYPERLINK("https://www.linkedin.com/vsearch/c?type=companies&keywords="&C15&"&orig=GLHD&rsid=&pageKey=biz-overview-internal&trkInfo=&search=Search")) -> https://www.linkedin.com/vsearch/c?type=companies&keywords=Dornbach IT Consulting GmbH&orig=GLHD&rsid=&pageKey=biz-overview-internal&trkInfo=&search=Search | M15: Sarah Klein | N15: Beratungshaus, benötigt Mandanten-getrennte Pipelines.
... B25: Agentur | C25: Studio Nordlicht GmbH | D25: Potenzieller Kunde | E25: 0431-667823 | F25: @studio-nordlicht.de | G25: www.studio-nordlicht.de | H25: Holstenstraße 41 | I25: Kiel | J25: 24103 | K25: DE | L25: =IF(C25="","-",HYPERLINK("https://www.linkedin.com/vsearch/c?type=companies&keywords="&C25&"&orig=GLHD&rsid=&pageKey=biz-overview-internal&trkInfo=&search=Search")) -> https://www.linkedin.com/vsearch/c?type=companies&keywords=Studio Nordlicht GmbH&orig=GLHD&rsid=&pageKey=biz-overview-internal&trkInfo=&search=Search | M25: Sarah Klein | N25: Sehr kleines Team, Interesse am Starter-Plan für 3 Nutzer.

Sheet Opportunities
C1: Geschäftschancen | D1: Copper-Tipp ➜ | E1: Bei einer Geschäftschance handelt es sich um jede Art einer Geschäftsentwicklungsbemühung, die Sie nachverfolgen und im Laufe eines Prozesses vorantreiben möchten. Achten Sie darauf, das voraussichtliche Abschlussdatum korrekt anzupassen. Dadurch können Sie genauere Prognosen für die zum Ende Ihres Verkaufszyklus erwarteten Umsätze treffen.
B3: Tag | C3: Name | D3: Unternehmen | E3: Phase | F3: Wert | G3: Abschlussdatum | H3: Gewinn in % | I3: Status | J3: Grund des Scheiterns | K3: Priorität | L3: Quelle | M3: Beschreibung | N3: Paket | O3: Nutzer | P3: Preis / Nutzer / Monat
B4: Bestandskunde | C4: LeadPilot Growth – Jahreslizenz | D4: Voss Antriebstechnik GmbH | E4: Bestätigt | F4: =O4*P4*12 -> 21360 | G4: 46037 | H4: 1 | I4: Erfolgreich | J4: Keiner | K4: Hoch | L4: Sonstige | M4: Verlängerung um 12 Monate, 20 Nutzer im Growth-Paket. | N4: Growth | O4: 20 | P4: 89
B5: Neukunde | C5: LeadPilot Einführung Rehbach | D5: Rehbach Fördertechnik GmbH | E5: Präsentation | F5: =O5*P5*12 -> 12816 | G5: 46275 | H5: 0.55 | I5: Offen | J5: Keiner | K5: Hoch | L5: Werbung | M5: Demo für 12 Nutzer im Außendienst geplant, Growth-Paket. | N5: Growth | O5: 12 | P5: 89
B6: Neukunde | C6: Pilotprojekt Kessler | D6: Kessler Präzisionswerk GmbH | E6: Nachverfolgung | F6: =O6*P6*12 -> 3528 | G6: 46296 | H6: 0.35 | I6: Offen | J6: Keiner | K6: Mittel | L6: Kaltakquise (Cold Call) | M6: Erstgespräch positiv, Budgetfreigabe ausstehend. Starter für 6 Nutzer. | N6: Starter | O6: 6 | P6: 49
B7: Upselling | C7: Nutzer-Erweiterung Brenner | D7: Brenner Hydraulik AG | E7: Verhandlung | F7: =O7*P7*12 -> 8544 | G7: 46254 | H7: 0.7 | I7: Offen | J7: Keiner | K7: Hoch | L7: Sonstige | M7: Erweiterung des bestehenden Growth-Vertrags um 8 Nutzer. | N7: Growth | O7: 8 | P7: 89
B8: Neukunde | C8: LeadPilot für Nordmeyer Vertriebsteam | D8: Nordmeyer Maschinenbau GmbH & Co. KG | E8: Präsentation | F8: =O8*P8*12 -> 11748 | G8: 46295 | H8: 0.5 | I8: Offen | J8: Keiner | K8: Mittel | L8: Werbung | M8: Interesse an automatisierter Lead-Priorisierung, 11 Nutzer. | N8: Growth | O8: 11 | P8: 89
B9: Partnerschaft | C9: Reseller-Vereinbarung Falkenrath | D9: Falkenrath Werkzeugmaschinen GmbH | E9: Nachverfolgung | F9: =O9*P9*12 -> 0 | G9: 46327 | H9: 0.2 | I9: Offen | J9: Keiner | K9: Niedrig | L9: Sonstige | M9: Prüft Vertriebspartnerschaft für Sachsen, kein direkter Umsatz. | N9: – | O9: 0 | P9: 0
B10: Bestandskunde | C10: LeadPilot Growth – Verlängerung | D10: Corvion Software GmbH | E10: Bestätigt | F10: =O10*P10*12 -> 10680 | G10: 46054 | H10: 1 | I10: Erfolgreich | J10: Keiner | K10: Hoch | L10: Sonstige | M10: Zweite Vertragsverlängerung über 10 Nutzer, Referenz für Case Study. | N10: Growth | O10: 10 | P10: 89
B11: Neukunde | C11: Wettbewerbsvergleich Bittner | D11: Bittner IT-Solutions GmbH | E11: Verhandlung | F11: =O11*P11*12 -> 13884 | G11: 46249 | H11: 0.6 | I11: Offen | J11: Keiner | K11: Hoch | L11: Kaltakquise (Cold Call) | M11: Vergleicht LeadPilot mit Pipedrive, Angebot über 13 Nutzer liegt vor. | N11: Growth | O11: 13 | P11: 89
B12: Neukunde | C12: Erstlizenz Pixelwerk | D12: Pixelwerk Digital GmbH | E12: Präsentation | F12: =O12*P12*12 -> 2352 | G12: 46270 | H12: 0.4 | I12: Offen | J12: Keiner | K12: Mittel | L12: E-Mail | M12: Erste Demo terminiert, kleines Team von 4 Nutzern. | N12: Starter | O12: 4 | P12: 49
B13: Bestandskunde | C13: LeadPilot Growth – Nutzer-Erweiterung | D13: Nexora Systems GmbH | E13: Vertrag gesendet | F13: =O13*P13*12 -> 6408 | G13: 46239 | H13: 0.85 | I13: Offen | J13: Keiner | K13: Hoch | L13: Sonstige | M13: Erweiterung von 8 auf 14 Nutzer, abgerechnet werden 6 zusätzliche Nutzer. | N13: Growth | O13: 6 | P13: 89
B14: Neukunde | C14: Starter-Paket Vantis | D14: Vantis Cloud Services GmbH | E14: Nachverfolgung | F14: =O14*P14*12 -> 2352 | G14: 46310 | H14: 0.3 | I14: Offen | J14: Keiner | K14: Niedrig | L14: Werbung | M14: Preissensibel, wartet auf Rabattangebot. Starter für 4 Nutzer. | N14: Starter | O14: 4 | P14: 49
B15: Neukunde | C15: Mandantenfähige Pipelines Dornbach | D15: Dornbach IT Consulting GmbH | E15: Präsentation | F15: =O15*P15*12 -> 7476 | G15: 46285 | H15: 0.45 | I15: Offen | J15: Keiner | K15: Mittel | L15: E-Mail | M15: Benötigt getrennte Pipelines je Mandant, Sonderkonfiguration in Prüfung. | N15: Growth | O15: 7 | P15: 89
... B27: Neukunde | C27: Pro-Angebot Dornbach | D27: Dornbach IT Consulting GmbH | E27: Verhandlung | F27: =O27*P27*12 -> 19200 | G27: 46341 | H27: 0.4 | I27: Offen | J27: Keiner | K27: Mittel | L27: E-Mail | M27: Alternative zum Growth-Angebot: Pro-Konditionen bei 20 Nutzern. | N27: Pro | O27: 20 | P27: 80
B29: Berechnungsregel | C29: Wert (Jahreswert) = Nutzer × Preis je Nutzer und Monat × 12. Starter 49 €, Growth 89 €, Pro nach individueller Vereinbarung (hier 80 €). Quelle: LeadPilot Faktenblatt v1.1, Abschnitt 2.

Sheet Interaktionen
C1: Interaktionen | D1: LeadPilot-Tipp ➤ | E1: Protokoll aller Vertriebskontakte (Anrufe, Demos, E-Mails, Meetings). Jede Interaktion erhält einen konkreten nächsten Schritt inklusive Fälligkeitsdatum, passend zu LeadPilots Kernfunktion der automatischen Lead-Priorisierung.
B3: Datum | C3: Unternehmen | D3: Kontakt | E3: Opportunity | F3: Interaktionstyp | G3: Kanal | H3: Zusammenfassung | I3: Ergebnis | J3: Nächster Schritt | K3: Fällig am | L3: Verantwortlicher
B4: 46175 | C4: Voss Antriebstechnik GmbH | D4: Michael Voss | E4: LeadPilot Professional - Jahreslizenz | F4: Anruf | G4: Telefon | H4: Jahresgespräch zur Vertragsverlängerung geführt. | I4: Erfolgreich abgeschlossen | J4: Zufriedenheits-Check nach 3 Monaten einplanen. | K4: 46267 | L4: Jonas Reiter
B5: 46193 | C5: Rehbach Fördertechnik GmbH | D5: Petra Rehbach | E5: LeadPilot Einführung Rehbach | F5: Demo | G5: Zoom | H5: Produktdemo für Vertriebsleitung und zwei Teamleiter durchgeführt. | I5: Positiv, hohes Interesse | J5: Angebot für 12 Nutzer erstellen und versenden. | K5: 46207 | L5: Sarah Klein
B6: 46208 | C6: Rehbach Fördertechnik GmbH | D6: Daniel Wagner | E6: LeadPilot Einführung Rehbach | F6: E-Mail | G6: E-Mail | H6: Angebot an Daniel Wagner als technischen Ansprechpartner versendet. | I6: Rückmeldung ausstehend | J6: Nachfassen, falls bis 18.07. keine Rückmeldung erfolgt. | K6: 46221 | L6: Sarah Klein
B7: 46184 | C7: Kessler Präzisionswerk GmbH | D7: Frank Kessler | E7: Pilotprojekt Kessler | F7: Anruf | G7: Telefon | H7: Kaltakquise-Anruf, Bedarf an strukturierter Lead-Nachverfolgung bestätigt. | I7: Interessiert | J7: Termin für Erstgespräch mit Entscheider vereinbaren. | K7: 46223 | L7: Tim Brandt
B8: 46218 | C8: Brenner Hydraulik AG | D8: Claudia Brenner | E8: Marketing-Modul Brenner | F8: Meeting vor Ort | G8: Vor Ort | H8: Vor-Ort-Termin zur Besprechung der Modul-Erweiterung. | I8: Verhandlung läuft | J8: Finales Angebot mit Rabattstaffel nachreichen. | K8: 46234 | L8: Jonas Reiter
B9: 46198 | C9: Nordmeyer Maschinenbau GmbH & Co. KG | D9: Stefan Nordmeyer | E9: LeadPilot für Nordmeyer Vertriebsteam | F9: Webinar-Teilnahme | G9: Online | H9: Teilnahme am Webinar 'Digitaler Vertrieb im Maschinenbau', im Nachgang kontaktiert. | I9: Interessiert | J9: Individuelle Demo mit Vertriebsteam terminieren. | K9: 46228 | L9: Sarah Klein
B10: 46213 | C10: Falkenrath Werkzeugmaschinen GmbH | D10: Robert Falkenrath | E10: Reseller-Vereinbarung Falkenrath | F10: Meeting vor Ort | G10: Vor Ort | H10: Gespräch über mögliche Vertriebspartnerschaft für Sachsen. | I10: Neutral, prüft intern | J10: In 4 Wochen erneut nachfassen. | K10: 46241 | L10: Nora Vogel
B11: 46170 | C11: Corvion Software GmbH | D11: Anna Corvin | E11: LeadPilot Professional - Verlängerung | F11: Anruf | G11: Telefon | H11: Verlängerungsgespräch, Zufriedenheit sehr hoch. | I11: Erfolgreich abgeschlossen | J11: Anfrage für Referenz-Case-Study stellen. | K11: 46235 | L11: Jonas Reiter
B12: 46211 | C12: Bittner IT-Solutions GmbH | D12: Julia Bittner | E12: Wettbewerbsvergleich Bittner | F12: Demo | G12: Zoom | H12: Vergleichsdemo LeadPilot vs. Pipedrive durchgeführt. | I12: Positiv, Entscheidung in 2 Wochen | J12: Referenzen von vergleichbaren IT-Dienstleistern zusenden. | K12: 46225 | L12: Tim Brandt
B13: 46221 | C13: Pixelwerk Digital GmbH | D13: Kevin Pauls | E13: Erstlizenz Pixelwerk | F13: E-Mail | G13: E-Mail | H13: Terminvorschläge für Erstdemo verschickt. | I13: Termin vereinbart | J13: Demo am 12.08. durchführen. | K13: 46246 | L13: Sarah Klein
B14: 46204 | C14: Nexora Systems GmbH | D14: Nadine Kurz | E14: LeadPilot Professional - Erweiterung | F14: Anruf | G14: Telefon | H14: Abstimmung zur Lizenzerweiterung von 8 auf 14 Nutzer. | I14: Erfolgreich, Vertrag folgt | J14: Vertragsunterlagen zur Unterschrift versenden. | K14: 46218 | L14: Jonas Reiter
B15: 46187 | C15: Vantis Cloud Services GmbH | D15: Tobias Vogt | E15: Starter-Paket Vantis | F15: LinkedIn-Nachricht | G15: LinkedIn | H15: Nachfrage zu Rabattmöglichkeiten für kleine Teams gestellt. | I15: Wartet auf Angebot | J15: Sonderkonditionen für Teams unter 5 Nutzern prüfen und anbieten. | K15: 46231 | L15: Tim Brandt
... B30: 46220 | C30: Dornbach IT Consulting GmbH | D30: Sabine Dornbach | E30: Enterprise-Angebot Dornbach | F30: Meeting vor Ort | G30: Vor Ort | H30: Besprechung eines Enterprise-Angebots als Alternative. | I30: Verhandlung läuft | J30: Angebotsvergleich Professional vs. Enterprise aufbereiten. | K30: 46244 | L30: Sarah Klein

Sheet Rahmenbedingungen
B1: Rahmenbedingungen
B3: Personen/Unternehmen | C3: Geschäftschancen
B4: Kontakttyp | C4: Phase | D4: Status | E4: Quelle | F4: Grund des Scheiterns
B5: ALLE | C5: ALLE | D5: ALLE | E5: ALLE | F5: ALLE
B6: Potenzieller Kunde | C6: Bestätigt | D6: Offen | E6: Werbung | F6: Mitbewerber
B7: Aktueller Kunde | C7: Nachverfolgung | D7: Erfolgreich | E7: Kaltakquise (Cold Call) | F7: Funktionen
B8: Sonstiger | C8: Präsentation | D8: Gescheitert | E8: E-Mail | F8: Preis
C9: Vertrag gesendet | D9: Abgebrochen | E9: Sonstige | F9: Keiner
C10: Verhandlung | D10: Verhandlung
