Workbook

Sheet Bilanz
B2: Bilanz zum 31. Dezember 2025
B3: LeadPilot GmbH, Leipzig · § 266 HGB · Angaben in EUR · fiktives Schulungsunternehmen
B5: AKTIVA (Mittelverwendung) | F5: PASSIVA (Mittelherkunft)
B6: Position | C6: 31.12.2025 | D6: 31.12.2024 | F6: Position | G6: 31.12.2025 | H6: 31.12.2024
B7: A. ANLAGEVERMÖGEN | F7: A. EIGENKAPITAL
B8: I. Immaterielle Vermögensgegenstände | C8: 22000 | D8: 16000 | F8: I. Gezeichnetes Kapital | G8: 31250 | H8: 31250
B9: II. Sachanlagen (Hardware, Geschäftsausstattung) | C9: 38000 | D9: 30000 | F9: II. Kapitalrücklage | G9: 1193750 | H9: 1193750
B10: Summe Anlagevermögen | C10: =SUM(C8:C9) | D10: =SUM(D8:D9) | F10: III. Verlustvortrag | G10: -547000 | H10: -240000
B11: B. UMLAUFVERMÖGEN | F11: IV. Jahresfehlbetrag | G11: -334000 | H11: -307000
B12: I. Forderungen aus Lieferungen und Leistungen | C12: 34000 | D12: 19000 | F12: Summe Eigenkapital | G12: =SUM(G8:G11) | H12: =SUM(H8:H11)
B13: II. Sonstige Vermögensgegenstände (USt, Kautionen) | C13: 14000 | D13: 9000 | F13: B. RÜCKSTELLUNGEN (Urlaub, Abschlusskosten) | G13: 30000 | H13: 22000
B14: III. Kassenbestand und Bankguthaben | C14: 363000 | D14: 686000 | F14: C. VERBINDLICHKEITEN
B15: Summe Umlaufvermögen | C15: =SUM(C12:C14) | D15: =SUM(D12:D14) | F15: Gegenüber Kreditinstituten (SAB-Innovationsdarlehen) | G15: 18000 | H15: 25000
B16: C. RECHNUNGSABGRENZUNGSPOSTEN | C16: 8000 | D16: 5000 | F16: Aus Lieferungen und Leistungen | G16: 21000 | H16: 13000
F17: Sonstige (Lohnsteuer, Sozialversicherung, USt) | G17: 28000 | H17: 13000
B18: BILANZSUMME AKTIVA | C18: =C10+C15+C16 | D18: =D10+D15+D16 | F18: Summe Verbindlichkeiten | G18: =SUM(G15:G17) | H18: =SUM(H15:H17)
F19: D. RECHNUNGSABGRENZUNGSPOSTEN (Jahresvorauszahlungen) | G19: 38000 | H19: 14000
F20: BILANZSUMME PASSIVA | G20: =G12+G13+G18+G19 | H20: =H12+H13+H18+H19
B22: Prüfung Bilanzgleichung (Aktiva − Passiva) | C22: =C18-G20 | D22: =D18-H20
B24: Fiktives Unternehmenskonzept im Rahmen der Weiterbildung Digital Sales Manager (DBA). Alle Werte orientieren sich an realen Größenordnungen deutscher B2B-SaaS-Unternehmen in der Seed-Phase. Quelle der Ansätze: LeadPilot Faktenblatt v1.1, Abschnitt 6.
B26: Position "II. Sonstige Vermögensgegenstände" (14.000 €) umfasst die Mietkaution von 8.550 € (3 Nettokaltmieten, Gewerberaummietvertrag v. 15.08.2022, Augustusplatz 9) sowie USt-Forderungen. Keine Sachanlage Grundstück/Gebäude – LeadPilot ist Mieterin, kein Grundbesitz.

Sheet GuV
B2: Gewinn- und Verlustrechnung 2025
B3: LeadPilot GmbH · Umsatzkostenverfahren · Angaben in EUR · negative Werte = Aufwand
B5: ERGEBNISRECHNUNG GESCHÄFTSJAHR 2025
B6: Position | C6: Q1 2025 | D6: Q2 2025 | E6: Q3 2025 | F6: Q4 2025 | G6: FY 2025 | H6: FY 2024 | I6: Δ % | J6: Anmerkung
B7: ERLÖSE
B8: Abo-Umsatz (wiederkehrend) | C8: 58559 | D8: 69281 | E8: 82152 | F8: 97608 | G8: =SUM(C8:F8) | H8: 149000 | I8: =IF(H8=0,"–",(G8-H8)/ABS(H8)) | J8: Kerngeschäft, MRR × 12 Monate
B9: Onboarding & Setup | C9: 4000 | D9: 5500 | E9: 6500 | F9: 7000 | G9: =SUM(C9:F9) | H9: 12000 | I9: =IF(H9=0,"–",(G9-H9)/ABS(H9)) | J9: Einmalgebühr Growth und Pro
B10: Sonstige Erlöse | C10: 1000 | D10: 1200 | E10: 1500 | F10: 1700 | G10: =SUM(C10:F10) | H10: 3000 | I10: =IF(H10=0,"–",(G10-H10)/ABS(H10)) | J10: API-Nutzung, Schulungen
B11: Umsatzerlöse | C11: =SUM(C8:C10) | D11: =SUM(D8:D10) | E11: =SUM(E8:E10) | F11: =SUM(F8:F10) | G11: =SUM(G8:G10) | H11: =SUM(H8:H10) | I11: =IF(H11=0,"–",(G11-H11)/ABS(H11))
B12: UMSATZKOSTEN
B13: Umsatzkosten (Hosting, KI-API, Customer Success) | C13: -23000 | D13: -27400 | E13: -32400 | F13: -38200 | G13: =SUM(C13:F13) | H13: -64000 | I13: =IF(H13=0,"–",(G13-H13)/ABS(H13)) | J13: davon 82.000 € Personal Customer Success
B14: Bruttogewinn | C14: =C11+C13 | D14: =D11+D13 | E14: =E11+E13 | F14: =F11+F13 | G14: =G11+G13 | H14: =H11+H13 | I14: =IF(H14=0,"–",(G14-H14)/ABS(H14))
B15: Bruttomarge | C15: =C14/C11 | D15: =D14/D11 | E15: =E14/E11 | F15: =F14/F11 | G15: =G14/G11 | H15: =H14/H11
B16: BETRIEBLICHE AUFWENDUNGEN
B17: Sales & Marketing | C17: -47500 | D17: -50500 | E17: -53500 | F17: -57500 | G17: =SUM(C17:F17) | H17: -141000 | I17: =IF(H17=0,"–",(G17-H17)/ABS(H17)) | J17: 3 FTE, Media-Spend 40.500 €
B18: Forschung & Entwicklung | C18: -47500 | D18: -50500 | E18: -53500 | F18: -56500 | G18: =SUM(C18:F18) | H18: -164000 | I18: =IF(H18=0,"–",(G18-H18)/ABS(H18)) | J18: 4 FTE Engineering und Product
B19: General & Administrative | C19: -25000 | D19: -26000 | E19: -27500 | F19: -28500 | G19: =SUM(C19:F19) | H19: -83000 | I19: =IF(H19=0,"–",(G19-H19)/ABS(H19)) | J19: Geschäftsführung, Miete, Recht
B20: EBITDA | C20: =C14+SUM(C17:C19) | D20: =D14+SUM(D17:D19) | E20: =E14+SUM(E17:E19) | F20: =F14+SUM(F17:F19) | G20: =G14+SUM(G17:G19) | H20: =H14+SUM(H17:H19) | I20: =IF(H20=0,"–",(G20-H20)/ABS(H20))
B21: Abschreibungen | C21: -4200 | D21: -4400 | E21: -4600 | F21: -4800 | G21: =SUM(C21:F21) | H21: -14000 | I21: =IF(H21=0,"–",(G21-H21)/ABS(H21)) | J21: Hardware, Geschäftsausstattung
B22: EBIT | C22: =C20+C21 | D22: =D20+D21 | E22: =E20+E21 | F22: =F20+F21 | G22: =G20+G21 | H22: =H20+H21 | I22: =IF(H22=0,"–",(G22-H22)/ABS(H22))
B23: Finanzergebnis | C23: -1300 | D23: -1400 | E23: -1400 | F23: -1400 | G23: =SUM(C23:F23) | H23: -4000 | I23: =IF(H23=0,"–",(G23-H23)/ABS(H23)) | J23: Zinsen SAB-Innovationsdarlehen
B24: Ergebnis vor Steuern | C24: =C22+C23 | D24: =D22+D23 | E24: =E22+E23 | F24: =F22+F23 | G24: =G22+G23 | H24: =H22+H23 | I24: =IF(H24=0,"–",(G24-H24)/ABS(H24))
B25: Sonstige Steuern | C25: -375 | D25: -375 | E25: -375 | F25: -375 | G25: =SUM(C25:F25) | H25: -1000 | I25: =IF(H25=0,"–",(G25-H25)/ABS(H25)) | J25: keine Ertragsteuern – Verlustjahr
B26: JAHRESFEHLBETRAG | C26: =C24+C25 | D26: =D24+D25 | E26: =E24+E25 | F26: =F24+F25 | G26: =G24+G25 | H26: =H24+H25 | I26: =G26/ABS(H26)-SIGN(H26)
B29: KOSTENSTRUKTUR NACH KOSTENART 2025
B30: Kostenart | C30: Betrag 2025 | D30: Anteil | J30: Erläuterung
B31: Personalaufwand gesamt (Ø 9 FTE) | C31: 490000 | D31: =C31/$C$40 | J31: Arbeitgeber-Gesamtkosten, Ø 54.400 € je FTE
B32: davon Customer Success (in Umsatzkosten) | C32: 82000 | D32: =C32/$C$40 | J32: 2 FTE zum Jahresende
B33: davon Forschung & Entwicklung | C33: 196000 | D33: =C33/$C$40 | J33: 4 FTE Engineering und Product
B34: davon Sales & Marketing | C34: 157000 | D34: =C34/$C$40 | J34: 2 FTE Sales, 1 FTE Marketing
B35: davon Geschäftsführung und Verwaltung | C35: 55000 | D35: =C35/$C$40 | J35: CEO / Ops
B36: Hosting, KI-API, Zahlungsabwicklung | C36: 39000 | D36: =C36/$C$40 | J36: europäische Rechenzentren, Frankfurt am Main
B37: Marketing-Media-Spend | C37: 40500 | D37: =C37/$C$40 | J37: LinkedIn, SEO, Webinare, Outbound
B38: Software, Tools, Lizenzen | C38: 23500 | D38: =C38/$C$40 | J38: Entwicklungs- und Vertriebs-Tools
B39: Miete, Recht, Buchhaltung, Versicherung | C39: 52000 | D39: =C39/$C$40 | J39: Büroflächen Augustusplatz 9, Leipzig – angemietet
B40: Gesamtaufwand (Umsatzkosten + OPEX) | C40: =C31+SUM(C36:C39)
B42: Abgleich: Gesamtaufwand entspricht Umsatzkosten (121.000 €) zuzüglich betrieblicher Aufwendungen (524.000 €) = 645.000 €. Ansätze und Herleitung: LeadPilot Faktenblatt v1.1, Abschnitt 5.
B44: Position "Miete, Recht, Buchhaltung, Versicherung" (52.000 €, siehe Zeile 39) gliedert sich in: Mietkosten Augustusplatz 9 39.800 € (Nettokaltmiete, Nebenkosten, 2 Stellplätze), Rechtsberatung 5.000 €, Buchhaltung/Steuerberatung 5.700 €, Versicherungen 1.500 € – gemäß Gewerberaummietvertrag v. 15.08.2022 mit der Augustusplatz Immobilien Leipzig GmbH & Co. KG.

Sheet Kennzahlen
B2: Bilanz- und Finanzkennzahlen
B3: abgeleitet aus Bilanz und GuV – alle Werte formelbasiert
B5: KENNZAHLEN AUS DEM JAHRESABSCHLUSS
B6: Kennzahl | C6: 2025 | D6: 2024 | E6: Zielwert | F6: Status | G6: Aussage
B7: Bilanzsumme | C7: =Bilanz!C18 | D7: =Bilanz!D18 | G7: Sinkt durch den Mittelverbrauch aus der Seed-Runde
B8: Eigenkapital | C8: =Bilanz!G12 | D8: =Bilanz!H12 | G8: Getragen von Stammkapital und Kapitalrücklage
B9: Eigenkapitalquote | C9: =Bilanz!G12/Bilanz!C18 | D9: =Bilanz!H12/Bilanz!D18 | E9: 0.4 | F9: erreicht | G9: Hoch, da eigenkapitalfinanziert und kaum Fremdkapital
B10: Liquide Mittel | C10: =Bilanz!C14 | D10: =Bilanz!D14 | E10: 300000 | F10: erreicht | G10: Runway von 14 Monaten zum 31.12.2025
B11: Umsatzerlöse | C11: =GuV!G11 | D11: =GuV!H11 | G11: Verdoppelung gegenüber dem Vorjahr
B12: Bruttomarge | C12: =GuV!G15 | D12: =GuV!H15 | E12: 0.68 | F12: knapp verfehlt | G12: Unter Ziel – KI-API-Kosten und CS-Aufwand belasten
B13: EBITDA | C13: =GuV!G20 | D13: =GuV!H20 | E13: -264000 | F13: verfehlt | G13: Entspricht der Burn Rate von 25.750 € pro Monat
B14: EBITDA-Marge | C14: =GuV!G20/GuV!G11 | D14: =GuV!H20/GuV!H11 | G14: Verbessert sich, bleibt aber deutlich negativ
B15: Jahresfehlbetrag | C15: =GuV!G26 | D15: =GuV!H26 | G15: Planmäßiger Verlust in der Wachstumsphase
B16: Burn Rate (Ø monatlich) | C16: =-GuV!G20/12 | D16: =-GuV!H20/12 | E16: 22000 | F16: verfehlt | G16: Ziel 2026: unter 23.000 € pro Monat
B17: Runway ab Bilanzstichtag | C17: =Bilanz!C14/(-GuV!G20/12) | D17: =Bilanz!D14/(-GuV!H20/12) | E17: 18 | F17: knapp verfehlt | G17: In Monaten – Anschlussfinanzierung ab Q3 2026 vorzubereiten
B18: Verschuldungsgrad | C18: =(Bilanz!G13+Bilanz!G18)/Bilanz!G12 | D18: =(Bilanz!H13+Bilanz!H18)/Bilanz!H12 | G18: Fremdkapital im Verhältnis zum Eigenkapital
B21: STEUERLICHE SITUATION
B22: Ertragsteuern 2025 | C22: 0 | G22: Verlustjahr – keine Körperschaft- und Gewerbesteuer
B23: Verlustvorträge zum 31.12.2025 (rund) | C23: 880000 | G23: Körperschaft- und Gewerbesteuer, kumuliert seit 2022
B24: Effektiver Steuersatz bei künftiger Profitabilität | C24: 0.319 | G24: KSt 15 % + SolZ 5,5 % + GewSt bei Leipziger Hebesatz von 460 %
B27: Alle Kennzahlen sind formelbasiert aus den Blättern Bilanz und GuV abgeleitet und rechnen bei Änderungen der Ausgangswerte automatisch nach. Fiktives Schulungsunternehmen – Größenordnungen orientiert an deutschen B2B-SaaS-Unternehmen in der Seed-Phase.
